{
  "id": "dc.anc_commissioner_seat:3A02",
  "family": "position",
  "kind": "dc.anc_commissioner_seat",
  "name": "Commissioner Seat for SMD 3A02",
  "attributes": {
    "currentHolderName": "Gracemary Allen",
    "officerRole": "Treasurer",
    "sourceAncId": "3A",
    "sourceFirstName": "GRACEMARY",
    "sourceLastName": "ALLEN",
    "sourceOancProfileUrl": "https://oanc.dc.gov/anc-profile/anc-3a",
    "sourcePageLastModified": "2026-06-16T20:56:42.000Z",
    "sourceRepresentativeName": "GRACEMARY ALLEN",
    "sourceSmdId": "3A02"
  },
  "citations": [
    {
      "source": "dcgis.smds",
      "sourceRecordId": "3A02"
    },
    {
      "source": "oanc.profiles",
      "sourceRecordId": "3A",
      "url": "https://oanc.dc.gov/anc-profile/anc-3a"
    }
  ],
  "relations": {
    "dc.relation:represents": [
      {
        "kind": "dc.relation:represents",
        "to": "dc.smd:3A02",
        "citations": [
          {
            "source": "dcgis.smds",
            "sourceRecordId": "3A02"
          }
        ]
      }
    ]
  }
}
