{
  "id": "dc.anc_commissioner_seat:5A08",
  "family": "position",
  "kind": "dc.anc_commissioner_seat",
  "name": "Commissioner Seat for SMD 5A08",
  "attributes": {
    "currentHolderName": "Elaine Alston",
    "officerRole": "Secretary",
    "sourceAncId": "5A",
    "sourceFirstName": "ELAINE",
    "sourceLastName": "ALSTON",
    "sourceOancProfileUrl": "https://oanc.dc.gov/anc-profile/anc-5a",
    "sourceRepresentativeName": "ELAINE ALSTON",
    "sourceSmdId": "5A08"
  },
  "citations": [
    {
      "source": "dcgis.smds",
      "sourceRecordId": "5A08"
    },
    {
      "source": "oanc.profiles",
      "sourceRecordId": "5A",
      "url": "https://oanc.dc.gov/anc-profile/anc-5a"
    }
  ],
  "relations": {
    "dc.relation:represents": [
      {
        "kind": "dc.relation:represents",
        "to": "dc.smd:5A08",
        "citations": [
          {
            "source": "dcgis.smds",
            "sourceRecordId": "5A08"
          }
        ]
      }
    ]
  }
}
