{
  "id": "dc.legal_authority:mayor-s-order-2012-49",
  "family": "authority",
  "kind": "dc.legal_authority",
  "name": "Mayor's Order 2012-49",
  "attributes": {
    "authorityType": "mayors_order",
    "canonicalUrl": "https://dcregs.dc.gov/Common/MayorOrders.aspx?Type=MayorOrder&OrderNumber=2012-49",
    "locator": "Mayor's Order 2012-49",
    "shortName": "Mayor's Order 2012-49"
  },
  "citations": [
    {
      "source": "open_dc.public_bodies",
      "sourceRecordId": "interagency-coordinating-council-icc",
      "locator": "Mayor's Order 2012-49"
    }
  ],
  "relations": {}
}
