{
  "id": "dc.legal_authority:d-c-code-8-1601",
  "family": "authority",
  "kind": "dc.legal_authority",
  "name": "D.C. Code § 8-1601",
  "attributes": {
    "authorityType": "dc_code",
    "canonicalUrl": "https://code.dccouncil.gov/us/dc/council/code/sections/8-1601",
    "locator": "D.C. Code § 8-1601",
    "shortName": "D.C. Code § 8-1601"
  },
  "citations": [
    {
      "source": "dcgis.commissions",
      "sourceRecordId": "135",
      "locator": "D.C. Code § 8-1601"
    },
    {
      "source": "open_dc.public_bodies",
      "sourceRecordId": "interstate-commission-potomac-river-basin-icprb",
      "locator": "D.C. Code § 8-1601"
    }
  ],
  "relations": {}
}
